foaap.py
foaap-2.3.1.dist-info/LICENSE
foaap-2.3.1.dist-info/WHEEL
foaap-2.3.1.dist-info/METADATA
foaap-2.3.1.dist-info/RECORD
