Metadata-Version: 2.1
Name: foaap
Version: 2.3.1
Summary: Fuck Off As A Package
Home-page: https://github.com/ilhomidin/foaap
License: MIT
Keywords: FOASS
Author: Ilhomidin Bahoraliev
Author-email: itilhomidin@yandex.com
Requires-Python: >=3.9,<4.0
Classifier: License :: OSI Approved :: MIT License
Classifier: Operating System :: OS Independent
Classifier: Programming Language :: Python :: 3
Classifier: Programming Language :: Python :: 3.9
Classifier: Topic :: Software Development :: Libraries :: Python Modules
Project-URL: Repository, https://github.com/ilhomidin/foaap
